dfm/__init__.py
dfm/config.py
dfm/hooks.py
dfm/links.py
dfm/mappings.py
dfm/profile.py
dfm/repo.py
dfm/cli/__init__.py
dfm/cli/add_cmd.py
dfm/cli/clean_cmd.py
dfm/cli/clone_cmd.py
dfm/cli/git_cmd.py
dfm/cli/init_cmd.py
dfm/cli/link_cmd.py
dfm/cli/list_cmd.py
dfm/cli/remove_cmd.py
dfm/cli/run_hook_cmd.py
dfm/cli/sync_cmd.py
dfm/cli/utils.py
dfm/cli/where_cmd.py
dfm-8.4.4.dist-info/METADATA
dfm-8.4.4.dist-info/WHEEL
dfm-8.4.4.dist-info/entry_points.txt
dfm-8.4.4.dist-info/top_level.txt
dfm-8.4.4.dist-info/RECORD
