Metadata-Version: 2.1
Name: dfm
Version: 8.4.4
Summary: A dotfile manager for pair-programmers and lazy people.
Home-page: https://github.com/chasinglogic/dfm
Author: Mathew Robinson
Author-email: chasinglogic@gmail.com
License: GPL-3.0
Platform: any
Classifier: Development Status :: 4 - Beta
Classifier: Environment :: Console
Classifier: Intended Audience :: Developers
Classifier: License :: OSI Approved :: GNU Affero General Public License v3
Classifier: Operating System :: POSIX
Classifier: Operating System :: MacOS
Classifier: Operating System :: Microsoft :: Windows
Classifier: Programming Language :: Python
Classifier: Programming Language :: Python :: 3
Classifier: Topic :: Software Development :: Libraries :: Python Modules
Requires-Dist: docopt
Requires-Dist: PyYAML (>=3.13)
